{"generator-jhipster":{"applicationType":"microservice","gitCompany":"","baseName":"jhipsterSampleApplication","packageName":"com.mycompany.myapp","packageFolder":"com/mycompany/myapp","serverPort":8081,"serviceDiscoveryType":"consul","authenticationType":"jwt","cacheProvider":"hazelcast","enableHibernateCache":true,"websocket":"spring-websocket","databaseType":"sql","devDatabaseType":"h2Disk","prodDatabaseType":"postgresql","searchEngine":"elasticsearch","enableSwaggerCodegen":"true","messageBroker":"kafka","buildTool":"maven","useSass":true,"clientPackageManager":"npm","testFrameworks":[],"enableTranslation":true,"nativeLanguage":"de","languages":["en","de"],"clientFramework":"angularX","jhiPrefix":"jhi","withAdminUi":true,"blueprints":[]},"git-provider":"GitHub","git-company":"singhfulda","repository-name":"jhipster-sample-application"}